substance/__init__.py
substance/_version.py
substance/box.py
substance/cli.py
substance/config.py
substance/constants.py
substance/core.py
substance/db.py
substance/engine.py
substance/exceptions.py
substance/hosts.py
substance/link.py
substance/logs.py
substance/monads.py
substance/orchestrator.py
substance/path.py
substance/platform.py
substance/shell.py
substance/termutils.py
substance/utils.py
substance/__pycache__/platform.cpython-39.pyc
substance/command/__init__.py
substance/command/aliases.py
substance/command/cleanup.py
substance/command/command.py
substance/command/docker.py
substance/command/exec.py
substance/command/expose.py
substance/command/fallback.py
substance/command/halt.py
substance/command/hatch.py
substance/command/help.py
substance/command/launch.py
substance/command/logs.py
substance/command/recreate.py
substance/command/restart.py
substance/command/run.py
substance/command/ssh.py
substance/command/start.py
substance/command/status.py
substance/command/stop.py
substance/command/suspend.py
substance/command/switch.py
substance/command/sync.py
substance/command/use.py
substance/command/box/__init__.py
substance/command/box/delete.py
substance/command/box/ls.py
substance/command/box/pull.py
substance/command/engine/__init__.py
substance/command/engine/create.py
substance/command/engine/delete.py
substance/command/engine/deprovision.py
substance/command/engine/edit.py
substance/command/engine/env.py
substance/command/engine/halt.py
substance/command/engine/launch.py
substance/command/engine/ls.py
substance/command/engine/ssh.py
substance/command/engine/sshinfo.py
substance/command/engine/suspend.py
substance/driver/__init__.py
substance/driver/virtualbox/__init__.py
substance/driver/virtualbox/exceptions.py
substance/driver/virtualbox/machine.py
substance/driver/virtualbox/network.py
substance/driver/virtualbox/vbox.py
substance/subenv/__init__.py
substance/subenv/api.py
substance/subenv/cli.py
substance/subenv/constants.py
substance-1.3.1.dist-info/LICENSE
substance-1.3.1.dist-info/METADATA
substance-1.3.1.dist-info/WHEEL
substance-1.3.1.dist-info/entry_points.txt
substance-1.3.1.dist-info/top_level.txt
substance-1.3.1.dist-info/RECORD
