Metadata-Version: 2.1
Name: substance
Version: 1.3.1
Summary: Substance - Local dockerized development environment
Home-page: https://substance.readthedocs.io/
Author: Turbulent
Author-email: oss@turbulent.ca
License: Apache License 2.0
Platform: UNKNOWN
Requires-Python: >=3
Requires-Dist: setuptools (>=1.1.3)
Requires-Dist: PyYAML
Requires-Dist: tabulate
Requires-Dist: paramiko (>=2.4.1)
Requires-Dist: netaddr
Requires-Dist: requests
Requires-Dist: tinydb
Requires-Dist: python-hosts (==0.3.3)
Requires-Dist: jinja2
Requires-Dist: macfsevents ; sys.platform == "darwin"
Requires-Dist: watchdog ; sys.platform == "linux"
